[
    {
        "date": 1730745000,
        "open": 247.34,
        "high": 255.28,
        "low": 246.21,
        "close": 251.44
    },
    {
        "date": 1730658600,
        "open": 244.56,
        "high": 248.9,
        "low": 238.88,
        "close": 242.84
    },
    {
        "date": 1730399400,
        "open": 252.04,
        "high": 254.0,
        "low": 246.63,
        "close": 248.98
    },
    {
        "date": 1730313000,
        "open": 257.99,
        "high": 259.75,
        "low": 249.25,
        "close": 249.85
    },
    {
        "date": 1730226600,
        "open": 258.04,
        "high": 263.35,
        "low": 255.82,
        "close": 257.55
    },
    {
        "date": 1730140200,
        "open": 264.51,
        "high": 264.98,
        "low": 255.51,
        "close": 259.52
    },
    {
        "date": 1730053800,
        "open": 270.0,
        "high": 273.54,
        "low": 262.24,
        "close": 262.51
    },
    {
        "date": 1729794600,
        "open": 256.01,
        "high": 269.49,
        "low": 255.32,
        "close": 269.19
    },
    {
        "date": 1729708200,
        "open": 244.68,
        "high": 262.12,
        "low": 242.65,
        "close": 260.48
    },
    {
        "date": 1729621800,
        "open": 217.13,
        "high": 218.72,
        "low": 212.11,
        "close": 213.65
    },
    {
        "date": 1729535400,
        "open": 217.31,
        "high": 218.22,
        "low": 215.26,
        "close": 217.97
    },
    {
        "date": 1729449000,
        "open": 218.9,
        "high": 220.48,
        "low": 215.73,
        "close": 218.85
    },
    {
        "date": 1729189800,
        "open": 220.71,
        "high": 222.28,
        "low": 219.23,
        "close": 220.7
    },
    {
        "date": 1729103400,
        "open": 221.59,
        "high": 222.08,
        "low": 217.9,
        "close": 220.89
    },
    {
        "date": 1729017000,
        "open": 221.4,
        "high": 222.82,
        "low": 218.93,
        "close": 221.33
    },
    {
        "date": 1728930600,
        "open": 220.01,
        "high": 224.26,
        "low": 217.12,
        "close": 219.57
    },
    {
        "date": 1728844200,
        "open": 220.13,
        "high": 221.91,
        "low": 213.74,
        "close": 219.16
    },
    {
        "date": 1728585000,
        "open": 220.13,
        "high": 223.34,
        "low": 214.38,
        "close": 217.8
    },
    {
        "date": 1728498600,
        "open": 241.81,
        "high": 242.79,
        "low": 232.34,
        "close": 238.77
    },
    {
        "date": 1728412200,
        "open": 243.82,
        "high": 247.43,
        "low": 239.51,
        "close": 241.05
    },
    {
        "date": 1728325800,
        "open": 243.56,
        "high": 246.21,
        "low": 240.56,
        "close": 244.5
    },
    {
        "date": 1728239400,
        "open": 249.0,
        "high": 249.83,
        "low": 240.7,
        "close": 240.83
    },
    {
        "date": 1727980200,
        "open": 246.69,
        "high": 250.96,
        "low": 244.58,
        "close": 250.08
    },
    {
        "date": 1727893800,
        "open": 244.48,
        "high": 249.79,
        "low": 237.81,
        "close": 240.66
    },
    {
        "date": 1727807400,
        "open": 247.55,
        "high": 251.16,
        "low": 241.5,
        "close": 249.02
    },
    {
        "date": 1727721000,
        "open": 262.67,
        "high": 263.98,
        "low": 248.53,
        "close": 258.02
    },
    {
        "date": 1727634600,
        "open": 259.04,
        "high": 264.86,
        "low": 255.77,
        "close": 261.63
    },
    {
        "date": 1727375400,
        "open": 257.38,
        "high": 260.7,
        "low": 254.12,
        "close": 260.46
    },
    {
        "date": 1727289000,
        "open": 260.6,
        "high": 261.75,
        "low": 251.53,
        "close": 254.22
    },
    {
        "date": 1727202600,
        "open": 252.54,
        "high": 257.05,
        "low": 252.28,
        "close": 257.02
    },
    {
        "date": 1727116200,
        "open": 254.08,
        "high": 257.19,
        "low": 249.05,
        "close": 254.27
    },
    {
        "date": 1727029800,
        "open": 242.61,
        "high": 250.0,
        "low": 241.92,
        "close": 250.0
    },
    {
        "date": 1726770600,
        "open": 241.52,
        "high": 243.99,
        "low": 235.92,
        "close": 238.25
    },
    {
        "date": 1726684200,
        "open": 234.0,
        "high": 244.24,
        "low": 232.13,
        "close": 243.92
    },
    {
        "date": 1726597800,
        "open": 230.09,
        "high": 235.68,
        "low": 226.88,
        "close": 227.2
    },
    {
        "date": 1726511400,
        "open": 229.45,
        "high": 234.57,
        "low": 226.55,
        "close": 227.87
    },
    {
        "date": 1726425000,
        "open": 229.3,
        "high": 229.96,
        "low": 223.53,
        "close": 226.78
    },
    {
        "date": 1726165800,
        "open": 228.0,
        "high": 232.67,
        "low": 226.32,
        "close": 230.29
    },
    {
        "date": 1726079400,
        "open": 224.66,
        "high": 231.45,
        "low": 223.83,
        "close": 229.81
    },
    {
        "date": 1725993000,
        "open": 224.55,
        "high": 228.47,
        "low": 216.8,
        "close": 228.13
    },
    {
        "date": 1725906600,
        "open": 220.07,
        "high": 226.4,
        "low": 218.64,
        "close": 226.17
    },
    {
        "date": 1725820200,
        "open": 216.2,
        "high": 219.87,
        "low": 213.67,
        "close": 216.27
    },
    {
        "date": 1725561000,
        "open": 232.6,
        "high": 233.6,
        "low": 210.51,
        "close": 210.73
    },
    {
        "date": 1725474600,
        "open": 223.49,
        "high": 235.0,
        "low": 222.25,
        "close": 230.17
    },
    {
        "date": 1725388200,
        "open": 210.59,
        "high": 222.22,
        "low": 210.57,
        "close": 219.41
    },
    {
        "date": 1725301800,
        "open": 215.26,
        "high": 219.9,
        "low": 209.64,
        "close": 210.6
    },
    {
        "date": 1724956200,
        "open": 208.63,
        "high": 214.57,
        "low": 207.03,
        "close": 214.11
    },
    {
        "date": 1724869800,
        "open": 209.8,
        "high": 214.89,
        "low": 205.97,
        "close": 206.28
    },
    {
        "date": 1724783400,
        "open": 209.72,
        "high": 211.84,
        "low": 202.59,
        "close": 205.75
    },
    {
        "date": 1724697000,
        "open": 213.25,
        "high": 215.66,
        "low": 206.94,
        "close": 209.21
    },
    {
        "date": 1724610600,
        "open": 218.75,
        "high": 219.09,
        "low": 211.01,
        "close": 213.21
    },
    {
        "date": 1724351400,
        "open": 214.46,
        "high": 221.48,
        "low": 214.21,
        "close": 220.32
    },
    {
        "date": 1724265000,
        "open": 223.82,
        "high": 224.8,
        "low": 210.32,
        "close": 210.66
    },
    {
        "date": 1724178600,
        "open": 222.67,
        "high": 224.66,
        "low": 218.86,
        "close": 223.27
    },
    {
        "date": 1724092200,
        "open": 224.88,
        "high": 228.22,
        "low": 219.56,
        "close": 221.1
    },
    {
        "date": 1724005800,
        "open": 217.07,
        "high": 222.98,
        "low": 214.09,
        "close": 222.72
    },
    {
        "date": 1723746600,
        "open": 211.15,
        "high": 219.8,
        "low": 210.8,
        "close": 216.12
    },
    {
        "date": 1723660200,
        "open": 205.02,
        "high": 215.88,
        "low": 204.82,
        "close": 214.14
    },
    {
        "date": 1723573800,
        "open": 207.39,
        "high": 208.44,
        "low": 198.75,
        "close": 201.38
    },
    {
        "date": 1723487400,
        "open": 198.47,
        "high": 208.49,
        "low": 197.06,
        "close": 207.83
    },
    {
        "date": 1723401000,
        "open": 199.02,
        "high": 199.26,
        "low": 194.67,
        "close": 197.49
    },
    {
        "date": 1723141800,
        "open": 197.05,
        "high": 200.88,
        "low": 195.11,
        "close": 200.0
    },
    {
        "date": 1723055400,
        "open": 195.7,
        "high": 200.7,
        "low": 192.04,
        "close": 198.84
    },
    {
        "date": 1722969000,
        "open": 200.77,
        "high": 203.49,
        "low": 191.48,
        "close": 191.76
    },
    {
        "date": 1722882600,
        "open": 200.75,
        "high": 202.9,
        "low": 192.67,
        "close": 200.64
    },
    {
        "date": 1722796200,
        "open": 185.22,
        "high": 203.88,
        "low": 182.0,
        "close": 198.88
    },
    {
        "date": 1722537000,
        "open": 214.88,
        "high": 216.13,
        "low": 205.78,
        "close": 207.67
    },
    {
        "date": 1722450600,
        "open": 227.69,
        "high": 231.87,
        "low": 214.33,
        "close": 216.86
    },
    {
        "date": 1722364200,
        "open": 227.9,
        "high": 234.68,
        "low": 226.79,
        "close": 232.07
    },
    {
        "date": 1722277800,
        "open": 232.25,
        "high": 232.41,
        "low": 220.0,
        "close": 222.62
    },
    {
        "date": 1722191400,
        "open": 224.9,
        "high": 234.27,
        "low": 224.7,
        "close": 232.1
    },
    {
        "date": 1721932200,
        "open": 221.19,
        "high": 222.28,
        "low": 215.33,
        "close": 219.8
    },
    {
        "date": 1721845800,
        "open": 216.8,
        "high": 226.0,
        "low": 216.23,
        "close": 220.25
    },
    {
        "date": 1721759400,
        "open": 225.42,
        "high": 225.99,
        "low": 214.71,
        "close": 215.99
    },
    {
        "date": 1721673000,
        "open": 253.6,
        "high": 255.76,
        "low": 245.63,
        "close": 246.38
    },
    {
        "date": 1721586600,
        "open": 244.21,
        "high": 253.21,
        "low": 243.75,
        "close": 251.51
    },
    {
        "date": 1721327400,
        "open": 247.79,
        "high": 249.44,
        "low": 236.83,
        "close": 239.2
    },
    {
        "date": 1721241000,
        "open": 251.09,
        "high": 257.14,
        "low": 247.2,
        "close": 249.23
    },
    {
        "date": 1721154600,
        "open": 252.73,
        "high": 258.47,
        "low": 246.18,
        "close": 248.5
    },
    {
        "date": 1721068200,
        "open": 255.31,
        "high": 258.62,
        "low": 245.8,
        "close": 256.56
    },
    {
        "date": 1720981800,
        "open": 255.97,
        "high": 265.6,
        "low": 251.73,
        "close": 252.64
    },
    {
        "date": 1720722600,
        "open": 235.8,
        "high": 251.84,
        "low": 233.09,
        "close": 248.23
    },
    {
        "date": 1720636200,
        "open": 263.3,
        "high": 271.0,
        "low": 239.65,
        "close": 241.03
    },
    {
        "date": 1720549800,
        "open": 262.8,
        "high": 267.59,
        "low": 257.86,
        "close": 263.26
    },
    {
        "date": 1720463400,
        "open": 251.0,
        "high": 265.61,
        "low": 250.3,
        "close": 262.33
    },
    {
        "date": 1720377000,
        "open": 247.71,
        "high": 259.44,
        "low": 244.57,
        "close": 252.94
    },
    {
        "date": 1720117800,
        "open": 249.81,
        "high": 252.37,
        "low": 242.46,
        "close": 251.52
    },
    {
        "date": 1719945000,
        "open": 234.56,
        "high": 248.35,
        "low": 234.25,
        "close": 246.39
    },
    {
        "date": 1719858600,
        "open": 218.89,
        "high": 231.3,
        "low": 218.06,
        "close": 231.26
    },
    {
        "date": 1719772200,
        "open": 201.02,
        "high": 213.23,
        "low": 200.85,
        "close": 209.86
    },
    {
        "date": 1719513000,
        "open": 199.55,
        "high": 203.2,
        "low": 195.26,
        "close": 197.88
    },
    {
        "date": 1719426600,
        "open": 195.17,
        "high": 198.72,
        "low": 194.05,
        "close": 197.42
    },
    {
        "date": 1719340200,
        "open": 186.54,
        "high": 197.76,
        "low": 186.36,
        "close": 196.37
    },
    {
        "date": 1719253800,
        "open": 184.4,
        "high": 187.97,
        "low": 182.01,
        "close": 187.35
    },
    {
        "date": 1719167400,
        "open": 184.97,
        "high": 188.8,
        "low": 182.55,
        "close": 182.58
    },
    {
        "date": 1718908200,
        "open": 182.3,
        "high": 183.95,
        "low": 180.69,
        "close": 183.01
    },
    {
        "date": 1718821800,
        "open": 184.68,
        "high": 185.21,
        "low": 179.66,
        "close": 181.57
    },
    {
        "date": 1718649000,
        "open": 186.56,
        "high": 187.2,
        "low": 182.37,
        "close": 184.86
    },
    {
        "date": 1718562600,
        "open": 177.92,
        "high": 188.81,
        "low": 177.0,
        "close": 187.44
    },
    {
        "date": 1718303400,
        "open": 185.8,
        "high": 186.0,
        "low": 176.92,
        "close": 178.01
    },
    {
        "date": 1718217000,
        "open": 188.39,
        "high": 191.08,
        "low": 181.23,
        "close": 182.47
    },
    {
        "date": 1718130600,
        "open": 171.12,
        "high": 180.55,
        "low": 169.8,
        "close": 177.29
    },
    {
        "date": 1718044200,
        "open": 173.92,
        "high": 174.75,
        "low": 167.41,
        "close": 170.66
    },
    {
        "date": 1717957800,
        "open": 176.06,
        "high": 178.57,
        "low": 173.17,
        "close": 173.79
    },
    {
        "date": 1717698600,
        "open": 176.13,
        "high": 179.35,
        "low": 175.58,
        "close": 177.48
    },
    {
        "date": 1717612200,
        "open": 174.6,
        "high": 179.73,
        "low": 172.73,
        "close": 177.94
    },
    {
        "date": 1717525800,
        "open": 175.35,
        "high": 176.15,
        "low": 172.13,
        "close": 175.0
    },
    {
        "date": 1717439400,
        "open": 174.78,
        "high": 177.76,
        "low": 174.0,
        "close": 174.77
    },
    {
        "date": 1717353000,
        "open": 178.13,
        "high": 182.64,
        "low": 174.49,
        "close": 176.29
    },
    {
        "date": 1717093800,
        "open": 178.5,
        "high": 180.32,
        "low": 173.82,
        "close": 178.08
    },
    {
        "date": 1717007400,
        "open": 178.58,
        "high": 182.67,
        "low": 175.38,
        "close": 178.79
    },
    {
        "date": 1716921000,
        "open": 174.19,
        "high": 178.15,
        "low": 173.93,
        "close": 176.19
    },
    {
        "date": 1716834600,
        "open": 176.4,
        "high": 178.25,
        "low": 173.16,
        "close": 176.75
    },
    {
        "date": 1716489000,
        "open": 174.84,
        "high": 180.08,
        "low": 173.73,
        "close": 179.24
    },
    {
        "date": 1716402600,
        "open": 181.8,
        "high": 181.9,
        "low": 173.26,
        "close": 173.74
    },
    {
        "date": 1716316200,
        "open": 182.85,
        "high": 183.8,
        "low": 178.12,
        "close": 180.11
    },
    {
        "date": 1716229800,
        "open": 175.51,
        "high": 186.88,
        "low": 174.71,
        "close": 186.6
    },
    {
        "date": 1716143400,
        "open": 177.56,
        "high": 177.75,
        "low": 173.52,
        "close": 174.95
    },
    {
        "date": 1715884200,
        "open": 173.55,
        "high": 179.63,
        "low": 172.75,
        "close": 177.46
    },
    {
        "date": 1715797800,
        "open": 174.1,
        "high": 175.79,
        "low": 171.43,
        "close": 174.84
    },
    {
        "date": 1715711400,
        "open": 179.9,
        "high": 180.0,
        "low": 173.11,
        "close": 173.99
    },
    {
        "date": 1715625000,
        "open": 174.5,
        "high": 179.49,
        "low": 174.07,
        "close": 177.55
    },
    {
        "date": 1715538600,
        "open": 170.0,
        "high": 175.4,
        "low": 169.0,
        "close": 171.89
    },
    {
        "date": 1715279400,
        "open": 173.05,
        "high": 173.06,
        "low": 167.75,
        "close": 168.47
    },
    {
        "date": 1715193000,
        "open": 175.01,
        "high": 175.62,
        "low": 171.37,
        "close": 171.97
    },
    {
        "date": 1715106600,
        "open": 171.59,
        "high": 176.06,
        "low": 170.15,
        "close": 174.72
    },
    {
        "date": 1715020200,
        "open": 182.4,
        "high": 183.26,
        "low": 177.4,
        "close": 177.81
    },
    {
        "date": 1714933800,
        "open": 183.8,
        "high": 187.56,
        "low": 182.2,
        "close": 184.76
    },
    {
        "date": 1714674600,
        "open": 182.1,
        "high": 184.78,
        "low": 178.42,
        "close": 181.19
    },
    {
        "date": 1714588200,
        "open": 182.86,
        "high": 184.6,
        "low": 176.02,
        "close": 180.01
    },
    {
        "date": 1714501800,
        "open": 182.0,
        "high": 185.86,
        "low": 179.01,
        "close": 179.99
    },
    {
        "date": 1714415400,
        "open": 186.98,
        "high": 190.95,
        "low": 182.84,
        "close": 183.28
    },
    {
        "date": 1714329000,
        "open": 188.42,
        "high": 198.87,
        "low": 184.54,
        "close": 194.05
    },
    {
        "date": 1714069800,
        "open": 168.85,
        "high": 172.12,
        "low": 166.37,
        "close": 168.29
    },
    {
        "date": 1713983400,
        "open": 158.96,
        "high": 170.88,
        "low": 158.36,
        "close": 170.18
    },
    {
        "date": 1713897000,
        "open": 162.84,
        "high": 167.97,
        "low": 157.51,
        "close": 162.13
    },
    {
        "date": 1713810600,
        "open": 143.33,
        "high": 147.26,
        "low": 141.11,
        "close": 144.68,
        "flag" : "True"
    },
    {
        "date": 1713724200,
        "open": 140.56,
        "high": 144.44,
        "low": 138.8,
        "close": 142.05
    },
    {
        "date": 1713465000,
        "open": 148.97,
        "high": 150.94,
        "low": 146.22,
        "close": 147.05
    },
    {
        "date": 1713378600,
        "open": 151.25,
        "high": 152.2,
        "low": 148.7,
        "close": 149.93
    },
    {
        "date": 1713292200,
        "open": 157.64,
        "high": 158.33,
        "low": 153.78,
        "close": 155.45
    },
    {
        "date": 1713205800,
        "open": 156.74,
        "high": 158.19,
        "low": 153.75,
        "close": 157.11
    },
    {
        "date": 1713119400,
        "open": 170.24,
        "high": 170.69,
        "low": 161.38,
        "close": 161.48
    },
    {
        "date": 1712860200,
        "open": 172.34,
        "high": 173.81,
        "low": 170.36,
        "close": 171.05
    },
    {
        "date": 1712773800,
        "open": 172.55,
        "high": 175.88,
        "low": 168.51,
        "close": 174.6
    },
    {
        "date": 1712687400,
        "open": 173.04,
        "high": 174.93,
        "low": 170.01,
        "close": 171.76
    },
    {
        "date": 1712601000,
        "open": 172.91,
        "high": 179.22,
        "low": 171.92,
        "close": 176.88
    },
    {
        "date": 1712514600,
        "open": 169.34,
        "high": 174.5,
        "low": 167.79,
        "close": 172.98
    },
    {
        "date": 1712255400,
        "open": 169.08,
        "high": 170.86,
        "low": 160.51,
        "close": 164.9
    },
    {
        "date": 1712169000,
        "open": 170.07,
        "high": 177.19,
        "low": 168.01,
        "close": 171.11
    },
    {
        "date": 1712082600,
        "open": 164.02,
        "high": 168.82,
        "low": 163.28,
        "close": 168.38
    },
    {
        "date": 1711996200,
        "open": 164.75,
        "high": 167.69,
        "low": 163.43,
        "close": 166.63
    },
    {
        "date": 1711909800,
        "open": 176.17,
        "high": 176.75,
        "low": 170.21,
        "close": 175.22
    },
    {
        "date": 1711564200,
        "open": 177.45,
        "high": 179.57,
        "low": 175.3,
        "close": 175.79
    },
    {
        "date": 1711477800,
        "open": 181.41,
        "high": 181.91,
        "low": 176.0,
        "close": 179.83
    },
    {
        "date": 1711391400,
        "open": 178.58,
        "high": 184.25,
        "low": 177.38,
        "close": 177.67
    },
    {
        "date": 1711305000,
        "open": 168.76,
        "high": 175.24,
        "low": 168.73,
        "close": 172.63
    },
    {
        "date": 1711045800,
        "open": 166.69,
        "high": 171.2,
        "low": 166.3,
        "close": 170.83
    },
    {
        "date": 1710959400,
        "open": 176.39,
        "high": 178.18,
        "low": 171.8,
        "close": 172.82
    },
    {
        "date": 1710873000,
        "open": 173.0,
        "high": 176.25,
        "low": 170.82,
        "close": 175.66
    },
    {
        "date": 1710786600,
        "open": 172.36,
        "high": 172.82,
        "low": 167.42,
        "close": 171.32
    },
    {
        "date": 1710700200,
        "open": 170.02,
        "high": 174.72,
        "low": 165.9,
        "close": 173.8
    },
    {
        "date": 1710441000,
        "open": 163.16,
        "high": 165.18,
        "low": 160.76,
        "close": 163.57
    },
    {
        "date": 1710354600,
        "open": 167.77,
        "high": 171.17,
        "low": 160.51,
        "close": 162.5,
        "flag" : "True"
    },
    {
        "date": 1710268200,
        "open": 173.05,
        "high": 176.05,
        "low": 169.15,
        "close": 169.48
    },
    {
        "date": 1710181800,
        "open": 177.77,
        "high": 179.43,
        "low": 172.41,
        "close": 177.54
    },
    {
        "date": 1710095400,
        "open": 175.45,
        "high": 182.87,
        "low": 174.8,
        "close": 177.77
    },
    {
        "date": 1709836200,
        "open": 181.5,
        "high": 182.73,
        "low": 174.7,
        "close": 175.34
    },
    {
        "date": 1709749800,
        "open": 174.35,
        "high": 180.04,
        "low": 173.7,
        "close": 178.65
    },
    {
        "date": 1709663400,
        "open": 179.99,
        "high": 181.58,
        "low": 173.7,
        "close": 176.54
    },
    {
        "date": 1709577000,
        "open": 183.05,
        "high": 184.59,
        "low": 177.57,
        "close": 180.74
    },
    {
        "date": 1709490600,
        "open": 198.73,
        "high": 199.75,
        "low": 186.72,
        "close": 188.14
    },
    {
        "date": 1709231400,
        "open": 200.52,
        "high": 204.52,
        "low": 198.5,
        "close": 202.64
    },
    {
        "date": 1709145000,
        "open": 204.18,
        "high": 205.28,
        "low": 198.45,
        "close": 201.88
    },
    {
        "date": 1709058600,
        "open": 200.42,
        "high": 205.3,
        "low": 198.44,
        "close": 202.04
    },
    {
        "date": 1708972200,
        "open": 204.04,
        "high": 205.6,
        "low": 198.26,
        "close": 199.73
    },
    {
        "date": 1708885800,
        "open": 192.29,
        "high": 201.78,
        "low": 192.0,
        "close": 199.4
    },
    {
        "date": 1708626600,
        "open": 195.31,
        "high": 197.57,
        "low": 191.5,
        "close": 191.97
    },
    {
        "date": 1708540200,
        "open": 194.0,
        "high": 198.32,
        "low": 191.36,
        "close": 197.41
    },
    {
        "date": 1708453800,
        "open": 193.36,
        "high": 199.44,
        "low": 191.95,
        "close": 194.77
    },
    {
        "date": 1708367400,
        "open": 196.13,
        "high": 198.6,
        "low": 189.13,
        "close": 193.76
    },
    {
        "date": 1708021800,
        "open": 202.06,
        "high": 203.17,
        "low": 197.4,
        "close": 199.95
    },
    {
        "date": 1707935400,
        "open": 189.16,
        "high": 200.88,
        "low": 188.86,
        "close": 200.45
    },
    {
        "date": 1707849000,
        "open": 185.3,
        "high": 188.89,
        "low": 183.35,
        "close": 188.71
    },
    {
        "date": 1707762600,
        "open": 183.99,
        "high": 187.26,
        "low": 182.11,
        "close": 184.02
    },
    {
        "date": 1707676200,
        "open": 192.11,
        "high": 194.73,
        "low": 187.28,
        "close": 188.13
    },
    {
        "date": 1707417000,
        "open": 190.18,
        "high": 194.12,
        "low": 189.48,
        "close": 193.57
    },
    {
        "date": 1707330600,
        "open": 189.0,
        "high": 191.62,
        "low": 185.58,
        "close": 189.56
    },
    {
        "date": 1707244200,
        "open": 188.18,
        "high": 189.79,
        "low": 182.68,
        "close": 187.58
    },
    {
        "date": 1707157800,
        "open": 177.21,
        "high": 186.49,
        "low": 177.11,
        "close": 185.1
    },
    {
        "date": 1707071400,
        "open": 184.26,
        "high": 184.68,
        "low": 175.01,
        "close": 181.06
    },
    {
        "date": 1706812200,
        "open": 185.04,
        "high": 188.69,
        "low": 182.0,
        "close": 187.91
    },
    {
        "date": 1706725800,
        "open": 188.5,
        "high": 189.88,
        "low": 184.28,
        "close": 188.86
    },
    {
        "date": 1706639400,
        "open": 187.0,
        "high": 193.97,
        "low": 185.85,
        "close": 187.29
    }
  ]
  